dico_interaction/__init__.py
dico_interaction/client.py
dico_interaction/command.py
dico_interaction/component.py
dico_interaction/context.py
dico_interaction/deco.py
dico_interaction/exception.py
dico_interaction/modal.py
dico_interaction/utils.py
dico_interaction/webserver.py
dico_interaction-0.0.9.dist-info/LICENSE
dico_interaction-0.0.9.dist-info/METADATA
dico_interaction-0.0.9.dist-info/WHEEL
dico_interaction-0.0.9.dist-info/top_level.txt
dico_interaction-0.0.9.dist-info/RECORD
