Metadata-Version: 2.1
Name: dico-interaction
Version: 0.0.9
Summary: Interaction module for dico.
Home-page: https://github.com/dico-api/dico-interaction
Author: eunwoo1104
Author-email: sions04@naver.com
License: UNKNOWN
Platform: UNKNOWN
Classifier: Programming Language :: Python :: 3
Requires-Python: >=3.7
License-File: LICENSE
Requires-Dist: dico-api
Requires-Dist: aiohttp
Provides-Extra: webserver
Requires-Dist: PyNaCl ; extra == 'webserver'
